cloudvoy/__init__.py
cloudvoy/config.py
cloudvoy/downloader.py
cloudvoy/dynamodb_manager.py
cloudvoy/instagram_uploader.py
cloudvoy/s3_uploader.py
cloudvoy/utils.py
cloudvoy/youtube.py
tests/__init__.py
tests/test_uploaders.py
CloudVoy-1.0.0.dist-info/METADATA
CloudVoy-1.0.0.dist-info/WHEEL
CloudVoy-1.0.0.dist-info/top_level.txt
CloudVoy-1.0.0.dist-info/RECORD
